{
  "goals": [
    {
      "gid": "g14",
      "title": "Clean Oceans",
      "nfts": [
        {
          "id": "1",
          "gid": "g14",
          "title": "Sea bin",
          "image": "https://picsum.photos/id/881/"
        },
        {
          "id": "2",
          "gid": "g14",
          "title": "Blah blah",
          "image": "https://picsum.photos/id/1069/"
        },
        {
          "id": "3",
          "gid": "g14",
          "title": "Blah blah",
          "image": "https://picsum.photos/id/1041/"
        }
      ]
    },
    {
      "gid": "g15",
      "title": "Reforestation",
      "nfts": [
        {
          "id": "4",
          "gid": "g15",
          "title": "Blah blah",
          "image": "https://picsum.photos/id/704/"
        },
        {
          "id": "5",
          "gid": "g15",

          "title": "Blah blah",
          "image": "https://picsum.photos/id/571/"
        },
        {
          "id": "6",
          "gid": "g15",

          "title": "Blah blah",
          "image": "https://picsum.photos/id/634/"
        }
      ]
    },

    {
      "gid": "g17",
      "title": "Community",
      "nfts": [
        {
          "id": "7",
          "gid": "g17",
          "title": "Blah blah",
          "image": "https://picsum.photos/id/830/"
        },
        {
          "id": "8",
          "gid": "g17",
          "title": "Blah blah",
          "image": "https://picsum.photos/id/906/"
        },
        {
          "id": "9",
          "gid": "g17",
          "title": "Blah blah",
          "image": "https://picsum.photos/id/287/"
        }
      ]
    }
  ]
}
